Workbook

Sheet Lightweight Freemium
B3: EW Navigation Product - Monetisation Impact Model for Lightweight Freemium
B4: Subscription price (Yearly) | C4: 69.99
E6: User Conversion & Retention Dynamics | M6: Revenue & Cost Breakdown | U6: Free User Monetisation Potential (B2B EW Office)
B7: Country | C7: Active Users D15 | E7: % CR | F7: Subscribers at D15 | G7: Non-Subscribers at D15 | H7: D30 Retention % (Free - Lightweight) | I7: Active Free Users D30 | J7: Monthly Retention % (Free Users) | K7: Avg Free User Lifetime (Months – Lightweight) | M7: Gross Revenue (€) | N7: App Store Fee (€) Cost | O7: Net Rev Pre-VAT (€) | P7: % VAT | Q7: VAT (€) Cost | R7: TTM Cost | S7: Net Revenue (€) | U7: Free Users Eligible for B2B Outreach | V7: Avg Reachable Lifetime (Months) | W7: Total Free-User Months Available | X7: % Drivers Eligible for B2B (Company / Owner-Drivers) | Y7: B2B-Relevant Free Users | Z7: Total B2B-Relevant Driver-Months | AA7: % B2B Users Exposed to Offer | AB7: B2B Users Exposed to Offer | AC7: B2B Offer Engagement Rate | AD7: Engaged B2B Users | AE7: Company Registration Rate | AF7: B2B Leads Generated | AG7: B2B Customer Activation Rate | AH7: Activated B2B Customers | AI7: Avg Annual Value per B2B Customer (€) | AJ7: Annual B2B Revenue Generated (€) | AK7: B2B Revenue vs Subscription Revenue Ratio
B8: PL | C8: 44869 | E8: 0.035 | F8: =C8*E8 -> 1570.415 | G8: =C8-F8 -> 43298.585 | H8: 0.7 | I8: =G8*H8 -> 30309.009 | J8: 0.95 | K8: =1/(1-J8) -> 20 | M8: =F8*C$4 -> 109913.35 | N8: =M8*30% -> 32974.004 | O8: =M8-N8 -> 76939.342 | P8: 0.23 | Q8: =O8*P8 -> 17696.049 | R8: =F8*4 -> 6281.66 | S8: =O8-Q8-R8 -> 52961.633 | U8: =I8 -> 30309.009 | V8: =K8 -> 20 | W8: =U8*V8 -> 606180.19 | X8: 0.3 | Y8: =U8*X8 -> 9092.7028 | Z8: =Y8*V8 -> 181854.06 | AA8: 0.5 | AB8: =Y8*AA8 -> 4546.3514 | AC8: 0.1 | AD8: =AB8*AC8 -> 454.63514 | AE8: 0.3 | AF8: =AD8*AE8 -> 136.39054 | AG8: 0.4 | AH8: =AF8*AG8 -> 54.556217 | AI8: 417 | AJ8: =AI8*AH8 -> 22749.943 | AK8: =AJ8/S8 -> 0.42955515
B9: FR | C9: 39623 | E9: 0.035 | F9: =C9*E9 -> 1386.805 | G9: =C9-F9 -> 38236.195 | H9: 0.7 | I9: =G9*H9 -> 26765.336 | J9: 0.95 | K9: =1/(1-J9) -> 20 | M9: =F9*C$4 -> 97062.482 | N9: =M9*30% -> 29118.745 | O9: =M9-N9 -> 67943.737 | P9: 0.2 | Q9: =O9*P9 -> 13588.747 | R9: =F9*4 -> 5547.22 | S9: =O9-Q9-R9 -> 48807.77 | U9: =I9 -> 26765.336 | V9: =K9 -> 20 | W9: =U9*V9 -> 535306.73 | X9: 0.3 | Y9: =U9*X9 -> 8029.6009 | Z9: =Y9*V9 -> 160592.02 | AA9: 0.5 | AB9: =Y9*AA9 -> 4014.8005 | AC9: 0.1 | AD9: =AB9*AC9 -> 401.48005 | AE9: 0.3 | AF9: =AD9*AE9 -> 120.44401 | AG9: 0.4 | AH9: =AF9*AG9 -> 48.177606 | AI9: 417 | AJ9: =AI9*AH9 -> 20090.062 | AK9: =AJ9/S9 -> 0.41161605
B10: GB | C10: 31541 | E10: 0.035 | F10: =C10*E10 -> 1103.935 | G10: =C10-F10 -> 30437.065 | H10: 0.7 | I10: =G10*H10 -> 21305.945 | J10: 0.95 | K10: =1/(1-J10) -> 20 | M10: =F10*C$4 -> 77264.411 | N10: =M10*30% -> 23179.323 | O10: =M10-N10 -> 54085.087 | P10: 0.2 | Q10: =O10*P10 -> 10817.017 | R10: =F10*4 -> 4415.74 | S10: =O10-Q10-R10 -> 38852.33 | U10: =I10 -> 21305.945 | V10: =K10 -> 20 | W10: =U10*V10 -> 426118.91 | X10: 0.3 | Y10: =U10*X10 -> 6391.7836 | Z10: =Y10*V10 -> 127835.67 | AA10: 0.5 | AB10: =Y10*AA10 -> 3195.8918 | AC10: 0.1 | AD10: =AB10*AC10 -> 319.58918 | AE10: 0.3 | AF10: =AD10*AE10 -> 95.876755 | AG10: 0.4 | AH10: =AF10*AG10 -> 38.350702 | AI10: 417 | AJ10: =AI10*AH10 -> 15992.243 | AK10: =AJ10/S10 -> 0.41161605
B11: DE | C11: 26636 | E11: 0.035 | F11: =C11*E11 -> 932.26 | G11: =C11-F11 -> 25703.74 | H11: 0.7 | I11: =G11*H11 -> 17992.618 | J11: 0.95 | K11: =1/(1-J11) -> 20 | M11: =F11*C$4 -> 65248.877 | N11: =M11*30% -> 19574.663 | O11: =M11-N11 -> 45674.214 | P11: 0.19 | Q11: =O11*P11 -> 8678.1007 | R11: =F11*4 -> 3729.04 | S11: =O11-Q11-R11 -> 33267.073 | U11: =I11 -> 17992.618 | V11: =K11 -> 20 | W11: =U11*V11 -> 359852.36 | X11: 0.3 | Y11: =U11*X11 -> 5397.7854 | Z11: =Y11*V11 -> 107955.71 | AA11: 0.5 | AB11: =Y11*AA11 -> 2698.8927 | AC11: 0.1 | AD11: =AB11*AC11 -> 269.88927 | AE11: 0.3 | AF11: =AD11*AE11 -> 80.966781 | AG11: 0.4 | AH11: =AF11*AG11 -> 32.386712 | AI11: 417 | AJ11: =AI11*AH11 -> 13505.259 | AK11: =AJ11/S11 -> 0.40596475
B12: IT | C12: 18105 | E12: 0.035 | F12: =C12*E12 -> 633.675 | G12: =C12-F12 -> 17471.325 | H12: 0.7 | I12: =G12*H12 -> 12229.927 | J12: 0.95 | K12: =1/(1-J12) -> 20 | M12: =F12*C$4 -> 44350.913 | N12: =M12*30% -> 13305.274 | O12: =M12-N12 -> 31045.639 | P12: 0.22 | Q12: =O12*P12 -> 6830.0406 | R12: =F12*4 -> 2534.7 | S12: =O12-Q12-R12 -> 21680.899 | U12: =I12 -> 12229.927 | V12: =K12 -> 20 | W12: =U12*V12 -> 244598.55 | X12: 0.3 | Y12: =U12*X12 -> 3668.9782 | Z12: =Y12*V12 -> 73379.565 | AA12: 0.5 | AB12: =Y12*AA12 -> 1834.4891 | AC12: 0.1 | AD12: =AB12*AC12 -> 183.44891 | AE12: 0.3 | AF12: =AD12*AE12 -> 55.034674 | AG12: 0.4 | AH12: =AF12*AG12 -> 22.01387 | AI12: 417 | AJ12: =AI12*AH12 -> 9179.7836 | AK12: =AJ12/S12 -> 0.4234042
B13: UA | C13: 12835 | E13: 0.035 | F13: =C13*E13 -> 449.225 | G13: =C13-F13 -> 12385.775 | H13: 0.7 | I13: =G13*H13 -> 8670.0425 | J13: 0.95 | K13: =1/(1-J13) -> 20 | M13: =F13*C$4 -> 31441.258 | N13: =M13*30% -> 9432.3773 | O13: =M13-N13 -> 22008.88 | P13: 0.2 | Q13: =O13*P13 -> 4401.7761 | R13: =F13*4 -> 1796.9 | S13: =O13-Q13-R13 -> 15810.204 | U13: =I13 -> 8670.0425 | V13: =K13 -> 20 | W13: =U13*V13 -> 173400.85 | X13: 0.3 | Y13: =U13*X13 -> 2601.0127 | Z13: =Y13*V13 -> 52020.255 | AA13: 0.5 | AB13: =Y13*AA13 -> 1300.5064 | AC13: 0.1 | AD13: =AB13*AC13 -> 130.05064 | AE13: 0.3 | AF13: =AD13*AE13 -> 39.015191 | AG13: 0.4 | AH13: =AF13*AG13 -> 15.606076 | AI13: 417 | AJ13: =AI13*AH13 -> 6507.7339 | AK13: =AJ13/S13 -> 0.41161605
B14: ES | C14: 17621 | E14: 0.035 | F14: =C14*E14 -> 616.735 | G14: =C14-F14 -> 17004.265 | H14: 0.7 | I14: =G14*H14 -> 11902.985 | J14: 0.95 | K14: =1/(1-J14) -> 20 | M14: =F14*C$4 -> 43165.283 | N14: =M14*30% -> 12949.585 | O14: =M14-N14 -> 30215.698 | P14: 0.21 | Q14: =O14*P14 -> 6345.2965 | R14: =F14*4 -> 2466.94 | S14: =O14-Q14-R14 -> 21403.461 | U14: =I14 -> 11902.985 | V14: =K14 -> 20 | W14: =U14*V14 -> 238059.71 | X14: 0.3 | Y14: =U14*X14 -> 3570.8956 | Z14: =Y14*V14 -> 71417.913 | AA14: 0.5 | AB14: =Y14*AA14 -> 1785.4478 | AC14: 0.1 | AD14: =AB14*AC14 -> 178.54478 | AE14: 0.3 | AF14: =AD14*AE14 -> 53.563435 | AG14: 0.4 | AH14: =AF14*AG14 -> 21.425374 | AI14: 417 | AJ14: =AI14*AH14 -> 8934.3809 | AK14: =AJ14/S14 -> 0.41742692
B15: CZ | C15: 10883 | E15: 0.035 | F15: =C15*E15 -> 380.905 | G15: =C15-F15 -> 10502.095 | H15: 0.7 | I15: =G15*H15 -> 7351.4665 | J15: 0.95 | K15: =1/(1-J15) -> 20 | M15: =F15*C$4 -> 26659.541 | N15: =M15*30% -> 7997.8623 | O15: =M15-N15 -> 18661.679 | P15: 0.21 | Q15: =O15*P15 -> 3918.9525 | R15: =F15*4 -> 1523.62 | S15: =O15-Q15-R15 -> 13219.106 | U15: =I15 -> 7351.4665 | V15: =K15 -> 20 | W15: =U15*V15 -> 147029.33 | X15: 0.3 | Y15: =U15*X15 -> 2205.4399 | Z15: =Y15*V15 -> 44108.799 | AA15: 0.5 | AB15: =Y15*AA15 -> 1102.72 | AC15: 0.1 | AD15: =AB15*AC15 -> 110.272 | AE15: 0.3 | AF15: =AD15*AE15 -> 33.081599 | AG15: 0.4 | AH15: =AF15*AG15 -> 13.23264 | AI15: 417 | AJ15: =AI15*AH15 -> 5518.0108 | AK15: =AJ15/S15 -> 0.41742692
B16: RO | C16: 10794 | E16: 0.035 | F16: =C16*E16 -> 377.79 | G16: =C16-F16 -> 10416.21 | H16: 0.7 | I16: =G16*H16 -> 7291.347 | J16: 0.95 | K16: =1/(1-J16) -> 20 | M16: =F16*C$4 -> 26441.522 | N16: =M16*30% -> 7932.4566 | O16: =M16-N16 -> 18509.065 | P16: 0.19 | Q16: =O16*P16 -> 3516.7224 | R16: =F16*4 -> 1511.16 | S16: =O16-Q16-R16 -> 13481.183 | U16: =I16 -> 7291.347 | V16: =K16 -> 20 | W16: =U16*V16 -> 145826.94 | X16: 0.3 | Y16: =U16*X16 -> 2187.4041 | Z16: =Y16*V16 -> 43748.082 | AA16: 0.5 | AB16: =Y16*AA16 -> 1093.702 | AC16: 0.1 | AD16: =AB16*AC16 -> 109.3702 | AE16: 0.3 | AF16: =AD16*AE16 -> 32.811062 | AG16: 0.4 | AH16: =AF16*AG16 -> 13.124425 | AI16: 417 | AJ16: =AI16*AH16 -> 5472.8851 | AK16: =AJ16/S16 -> 0.40596475
B17: HU | C17: 6912 | E17: 0.035 | F17: =C17*E17 -> 241.92 | G17: =C17-F17 -> 6670.08 | H17: 0.7 | I17: =G17*H17 -> 4669.056 | J17: 0.95 | K17: =1/(1-J17) -> 20 | M17: =F17*C$4 -> 16931.981 | N17: =M17*30% -> 5079.5942 | O17: =M17-N17 -> 11852.387 | P17: 0.27 | Q17: =O17*P17 -> 3200.1444 | R17: =F17*4 -> 967.68 | S17: =O17-Q17-R17 -> 7684.5622 | U17: =I17 -> 4669.056 | V17: =K17 -> 20 | W17: =U17*V17 -> 93381.12 | X17: 0.3 | Y17: =U17*X17 -> 1400.7168 | Z17: =Y17*V17 -> 28014.336 | AA17: 0.5 | AB17: =Y17*AA17 -> 700.3584 | AC17: 0.1 | AD17: =AB17*AC17 -> 70.03584 | AE17: 0.3 | AF17: =AD17*AE17 -> 21.010752 | AG17: 0.4 | AH17: =AF17*AG17 -> 8.4043008 | AI17: 417 | AJ17: =AI17*AH17 -> 3504.5934 | AK17: =AJ17/S17 -> 0.45605636

Sheet Hard Paywall
B3: EW Navigation Product - Monetisation Impact Model for Hard Paywall
B4: Subscription price (Yearly) | C4: 69.99
E6: User Conversion & Retention Dynamics | M6: Revenue & Cost Breakdown | U6: Free User Monetisation Potential (B2B EW Office)
B7: Country | C7: Active Users D15 | E7: % CR | F7: Subscribers at D15 | G7: Non-Subscribers at D15 | H7: D30 Retention % (Hard Paywall) | I7: Active Free Users D30 | J7: Monthly Retention % (Hard Paywall) | K7: Avg Free User Lifetime (Months – Hard Paywall) | M7: Gross Revenue (€) | N7: App Store Fee (€) Cost | O7: Net Rev Pre-VAT (€) | P7: % VAT | Q7: VAT (€) Cost | R7: TTM Cost | S7: Net Revenue (€) | U7: Free Users Eligible for B2B Outreach | V7: Avg Reachable Lifetime (Months) | W7: Total Free-User Months Available | X7: % Drivers Eligible for B2B (Company / Owner-Drivers) | Y7: B2B-Relevant Free Users | Z7: Total B2B-Relevant Driver-Months | AA7: % B2B Users Exposed to Offer | AB7: B2B Users Exposed to Offer | AC7: B2B Offer Engagement Rate | AD7: Engaged B2B Users | AE7: Company Registration Rate | AF7: B2B Leads Generated | AG7: B2B Customer Activation Rate | AH7: Activated B2B Customers | AI7: Avg Annual Value per B2B Customer (€) | AJ7: Annual B2B Revenue Generated (€) | AK7: B2B Revenue vs Subscription Revenue Ratio
B8: PL | C8: 44869 | E8: 0.035 | F8: =C8*E8 -> 1570.415 | G8: =C8-F8 -> 43298.585 | H8: 0.05 | I8: =G8*H8 -> 2164.9293 | J8: 0.5 | K8: =1/(1-J8) -> 2 | M8: =F8*C$4 -> 109913.35 | N8: =M8*30% -> 32974.004 | O8: =M8-N8 -> 76939.342 | P8: 0.23 | Q8: =O8*P8 -> 17696.049 | R8: =F8*4 -> 6281.66 | S8: =O8-Q8-R8 -> 52961.633 | U8: =I8 -> 2164.9293 | V8: =K8 -> 2 | W8: =U8*V8 -> 4329.8585 | X8: 0.3 | Y8: =U8*X8 -> 649.47878 | Z8: =Y8*V8 -> 1298.9576 | AA8: 0.5 | AB8: =Y8*AA8 -> 324.73939 | AC8: 0.1 | AD8: =AB8*AC8 -> 32.473939 | AE8: 0.3 | AF8: =AD8*AE8 -> 9.7421816 | AG8: 0.4 | AH8: =AF8*AG8 -> 3.8968727 | AI8: 417 | AJ8: =AI8*AH8 -> 1624.9959 | AK8: =AJ8/S8 -> 0.030682511
B9: FR | C9: 39623 | E9: 0.035 | F9: =C9*E9 -> 1386.805 | G9: =C9-F9 -> 38236.195 | H9: 0.05 | I9: =G9*H9 -> 1911.8098 | J9: 0.5 | K9: =1/(1-J9) -> 2 | M9: =F9*C$4 -> 97062.482 | N9: =M9*30% -> 29118.745 | O9: =M9-N9 -> 67943.737 | P9: 0.2 | Q9: =O9*P9 -> 13588.747 | R9: =F9*4 -> 5547.22 | S9: =O9-Q9-R9 -> 48807.77 | U9: =I9 -> 1911.8098 | V9: =K9 -> 2 | W9: =U9*V9 -> 3823.6195 | X9: 0.3 | Y9: =U9*X9 -> 573.54292 | Z9: =Y9*V9 -> 1147.0858 | AA9: 0.5 | AB9: =Y9*AA9 -> 286.77146 | AC9: 0.1 | AD9: =AB9*AC9 -> 28.677146 | AE9: 0.3 | AF9: =AD9*AE9 -> 8.6031439 | AG9: 0.4 | AH9: =AF9*AG9 -> 3.4412575 | AI9: 417 | AJ9: =AI9*AH9 -> 1435.0044 | AK9: =AJ9/S9 -> 0.029401147
B10: GB | C10: 31541 | E10: 0.035 | F10: =C10*E10 -> 1103.935 | G10: =C10-F10 -> 30437.065 | H10: 0.05 | I10: =G10*H10 -> 1521.8533 | J10: 0.5 | K10: =1/(1-J10) -> 2 | M10: =F10*C$4 -> 77264.411 | N10: =M10*30% -> 23179.323 | O10: =M10-N10 -> 54085.087 | P10: 0.2 | Q10: =O10*P10 -> 10817.017 | R10: =F10*4 -> 4415.74 | S10: =O10-Q10-R10 -> 38852.33 | U10: =I10 -> 1521.8533 | V10: =K10 -> 2 | W10: =U10*V10 -> 3043.7065 | X10: 0.3 | Y10: =U10*X10 -> 456.55598 | Z10: =Y10*V10 -> 913.11195 | AA10: 0.5 | AB10: =Y10*AA10 -> 228.27799 | AC10: 0.1 | AD10: =AB10*AC10 -> 22.827799 | AE10: 0.3 | AF10: =AD10*AE10 -> 6.8483396 | AG10: 0.4 | AH10: =AF10*AG10 -> 2.7393359 | AI10: 417 | AJ10: =AI10*AH10 -> 1142.303 | AK10: =AJ10/S10 -> 0.029401147
B11: DE | C11: 26636 | E11: 0.035 | F11: =C11*E11 -> 932.26 | G11: =C11-F11 -> 25703.74 | H11: 0.05 | I11: =G11*H11 -> 1285.187 | J11: 0.5 | K11: =1/(1-J11) -> 2 | M11: =F11*C$4 -> 65248.877 | N11: =M11*30% -> 19574.663 | O11: =M11-N11 -> 45674.214 | P11: 0.19 | Q11: =O11*P11 -> 8678.1007 | R11: =F11*4 -> 3729.04 | S11: =O11-Q11-R11 -> 33267.073 | U11: =I11 -> 1285.187 | V11: =K11 -> 2 | W11: =U11*V11 -> 2570.374 | X11: 0.3 | Y11: =U11*X11 -> 385.5561 | Z11: =Y11*V11 -> 771.1122 | AA11: 0.5 | AB11: =Y11*AA11 -> 192.77805 | AC11: 0.1 | AD11: =AB11*AC11 -> 19.277805 | AE11: 0.3 | AF11: =AD11*AE11 -> 5.7833415 | AG11: 0.4 | AH11: =AF11*AG11 -> 2.3133366 | AI11: 417 | AJ11: =AI11*AH11 -> 964.66136 | AK11: =AJ11/S11 -> 0.028997482
B12: IT | C12: 18105 | E12: 0.035 | F12: =C12*E12 -> 633.675 | G12: =C12-F12 -> 17471.325 | H12: 0.05 | I12: =G12*H12 -> 873.56625 | J12: 0.5 | K12: =1/(1-J12) -> 2 | M12: =F12*C$4 -> 44350.913 | N12: =M12*30% -> 13305.274 | O12: =M12-N12 -> 31045.639 | P12: 0.22 | Q12: =O12*P12 -> 6830.0406 | R12: =F12*4 -> 2534.7 | S12: =O12-Q12-R12 -> 21680.899 | U12: =I12 -> 873.56625 | V12: =K12 -> 2 | W12: =U12*V12 -> 1747.1325 | X12: 0.3 | Y12: =U12*X12 -> 262.06988 | Z12: =Y12*V12 -> 524.13975 | AA12: 0.5 | AB12: =Y12*AA12 -> 131.03494 | AC12: 0.1 | AD12: =AB12*AC12 -> 13.103494 | AE12: 0.3 | AF12: =AD12*AE12 -> 3.9310481 | AG12: 0.4 | AH12: =AF12*AG12 -> 1.5724193 | AI12: 417 | AJ12: =AI12*AH12 -> 655.69883 | AK12: =AJ12/S12 -> 0.030243157
B13: UA | C13: 12835 | E13: 0.035 | F13: =C13*E13 -> 449.225 | G13: =C13-F13 -> 12385.775 | H13: 0.05 | I13: =G13*H13 -> 619.28875 | J13: 0.5 | K13: =1/(1-J13) -> 2 | M13: =F13*C$4 -> 31441.258 | N13: =M13*30% -> 9432.3773 | O13: =M13-N13 -> 22008.88 | P13: 0.2 | Q13: =O13*P13 -> 4401.7761 | R13: =F13*4 -> 1796.9 | S13: =O13-Q13-R13 -> 15810.204 | U13: =I13 -> 619.28875 | V13: =K13 -> 2 | W13: =U13*V13 -> 1238.5775 | X13: 0.3 | Y13: =U13*X13 -> 185.78663 | Z13: =Y13*V13 -> 371.57325 | AA13: 0.5 | AB13: =Y13*AA13 -> 92.893313 | AC13: 0.1 | AD13: =AB13*AC13 -> 9.2893313 | AE13: 0.3 | AF13: =AD13*AE13 -> 2.7867994 | AG13: 0.4 | AH13: =AF13*AG13 -> 1.1147198 | AI13: 417 | AJ13: =AI13*AH13 -> 464.83814 | AK13: =AJ13/S13 -> 0.029401147
B14: ES | C14: 17621 | E14: 0.035 | F14: =C14*E14 -> 616.735 | G14: =C14-F14 -> 17004.265 | H14: 0.05 | I14: =G14*H14 -> 850.21325 | J14: 0.5 | K14: =1/(1-J14) -> 2 | M14: =F14*C$4 -> 43165.283 | N14: =M14*30% -> 12949.585 | O14: =M14-N14 -> 30215.698 | P14: 0.21 | Q14: =O14*P14 -> 6345.2965 | R14: =F14*4 -> 2466.94 | S14: =O14-Q14-R14 -> 21403.461 | U14: =I14 -> 850.21325 | V14: =K14 -> 2 | W14: =U14*V14 -> 1700.4265 | X14: 0.3 | Y14: =U14*X14 -> 255.06397 | Z14: =Y14*V14 -> 510.12795 | AA14: 0.5 | AB14: =Y14*AA14 -> 127.53199 | AC14: 0.1 | AD14: =AB14*AC14 -> 12.753199 | AE14: 0.3 | AF14: =AD14*AE14 -> 3.8259596 | AG14: 0.4 | AH14: =AF14*AG14 -> 1.5303839 | AI14: 417 | AJ14: =AI14*AH14 -> 638.17007 | AK14: =AJ14/S14 -> 0.029816209
B15: CZ | C15: 10883 | E15: 0.035 | F15: =C15*E15 -> 380.905 | G15: =C15-F15 -> 10502.095 | H15: 0.05 | I15: =G15*H15 -> 525.10475 | J15: 0.5 | K15: =1/(1-J15) -> 2 | M15: =F15*C$4 -> 26659.541 | N15: =M15*30% -> 7997.8623 | O15: =M15-N15 -> 18661.679 | P15: 0.21 | Q15: =O15*P15 -> 3918.9525 | R15: =F15*4 -> 1523.62 | S15: =O15-Q15-R15 -> 13219.106 | U15: =I15 -> 525.10475 | V15: =K15 -> 2 | W15: =U15*V15 -> 1050.2095 | X15: 0.3 | Y15: =U15*X15 -> 157.53142 | Z15: =Y15*V15 -> 315.06285 | AA15: 0.5 | AB15: =Y15*AA15 -> 78.765712 | AC15: 0.1 | AD15: =AB15*AC15 -> 7.8765712 | AE15: 0.3 | AF15: =AD15*AE15 -> 2.3629714 | AG15: 0.4 | AH15: =AF15*AG15 -> 0.94518855 | AI15: 417 | AJ15: =AI15*AH15 -> 394.14363 | AK15: =AJ15/S15 -> 0.029816209
B16: RO | C16: 10794 | E16: 0.035 | F16: =C16*E16 -> 377.79 | G16: =C16-F16 -> 10416.21 | H16: 0.05 | I16: =G16*H16 -> 520.8105 | J16: 0.5 | K16: =1/(1-J16) -> 2 | M16: =F16*C$4 -> 26441.522 | N16: =M16*30% -> 7932.4566 | O16: =M16-N16 -> 18509.065 | P16: 0.19 | Q16: =O16*P16 -> 3516.7224 | R16: =F16*4 -> 1511.16 | S16: =O16-Q16-R16 -> 13481.183 | U16: =I16 -> 520.8105 | V16: =K16 -> 2 | W16: =U16*V16 -> 1041.621 | X16: 0.3 | Y16: =U16*X16 -> 156.24315 | Z16: =Y16*V16 -> 312.4863 | AA16: 0.5 | AB16: =Y16*AA16 -> 78.121575 | AC16: 0.1 | AD16: =AB16*AC16 -> 7.8121575 | AE16: 0.3 | AF16: =AD16*AE16 -> 2.3436472 | AG16: 0.4 | AH16: =AF16*AG16 -> 0.9374589 | AI16: 417 | AJ16: =AI16*AH16 -> 390.92036 | AK16: =AJ16/S16 -> 0.028997482
B17: HU | C17: 6912 | E17: 0.035 | F17: =C17*E17 -> 241.92 | G17: =C17-F17 -> 6670.08 | H17: 0.05 | I17: =G17*H17 -> 333.504 | J17: 0.5 | K17: =1/(1-J17) -> 2 | M17: =F17*C$4 -> 16931.981 | N17: =M17*30% -> 5079.5942 | O17: =M17-N17 -> 11852.387 | P17: 0.27 | Q17: =O17*P17 -> 3200.1444 | R17: =F17*4 -> 967.68 | S17: =O17-Q17-R17 -> 7684.5622 | U17: =I17 -> 333.504 | V17: =K17 -> 2 | W17: =U17*V17 -> 667.008 | X17: 0.3 | Y17: =U17*X17 -> 100.0512 | Z17: =Y17*V17 -> 200.1024 | AA17: 0.5 | AB17: =Y17*AA17 -> 50.0256 | AC17: 0.1 | AD17: =AB17*AC17 -> 5.00256 | AE17: 0.3 | AF17: =AD17*AE17 -> 1.500768 | AG17: 0.4 | AH17: =AF17*AG17 -> 0.6003072 | AI17: 417 | AJ17: =AI17*AH17 -> 250.3281 | AK17: =AJ17/S17 -> 0.032575454

Sheet LFr vs HPw Summary
B3: EW Navigation Product - Lightweight Freemium vs Hard Paywall (Summary)
C6: User Behaviour & Retention | H6: Monetisation Outcomes
B7: Metric | C7: Light | D7: Hard | E7: Delta (Hard – Light) | G7: Metric | H7: Light | I7: Hard | J7: Delta (Hard – Light)
B8: Active Users at D15 | C8: =SUM('Lightweight Freemium'!C$8:C$17) -> 219819 | D8: =SUM('Hard Paywall'!C$8:C$17) -> 219819 | E8: =D8-C8 -> 0 | G8: Year-1 Subscription Net Revenue (€) | H8: =SUM('Lightweight Freemium'!S$8:S$17) -> 267168.22 | I8: =SUM('Hard Paywall'!S$8:S$17) -> 267168.22 | J8: =I8-H8 -> 0
B9: Subscribers at D15 | C9: =SUM('Lightweight Freemium'!F$8:F$17) -> 7693.665 | D9: =SUM('Hard Paywall'!F$8:F$17) -> 7693.665 | E9: =D9-C9 -> 0 | G9: Annual B2B Revenue (€) | H9: =SUM('Lightweight Freemium'!AJ$8:AJ$17) -> 111454.89 | I9: =SUM('Hard Paywall'!AJ$8:AJ$17) -> 7961.0638 | J9: =I9-H9 -> -103493.83
B10: Non-Subscribers at D15 | C10: =SUM('Lightweight Freemium'!G$8:G$17) -> 212125.33 | D10: =SUM('Hard Paywall'!G$8:G$17) -> 212125.33 | E10: =D10-C10 -> 0 | G10: Total Annual Value (€) | H10: =SUM(H8:H9) -> 378623.12 | I10: =SUM(I8:I9) -> 275129.29 | J10: =I10-H10 -> -103493.83
B11: D30 Retention (Free Users) | C11: =AVERAGE('Lightweight Freemium'!H$8:H$17) -> 0.7 | D11: =AVERAGE('Hard Paywall'!H$8:H$17) -> 0.05 | E11: =D11-C11 -> -0.65
B12: Active Free Users D30 | C12: =SUM('Lightweight Freemium'!I$8:I$17) -> 148487.73 | D12: =SUM('Hard Paywall'!I$8:I$17) -> 10606.267 | E12: =D12-C12 -> -137881.47
B13: Avg Free User Lifetime (Months) | C13: =AVERAGE('Lightweight Freemium'!K$8:K$17) -> 20 | D13: =AVERAGE('Hard Paywall'!K$8:K$17) -> 2 | E13: =D13-C13 -> -18
C15: B2B Reach & Lead Generation | H15: Efficiency & Strategic Ratios
B16: Metric | C16: Light | D16: Hard | E16: Delta (Hard – Light) | G16: Metric | H16: Light | I16: Hard | J16: Delta (Hard – Light)
B17: Free Users Eligible for B2B Outreach | C17: =SUM('Lightweight Freemium'!U$8:U$17) -> 148487.73 | D17: =SUM('Hard Paywall'!U$8:U$17) -> 10606.267 | E17: =D17-C17 -> -137881.47 | G17: B2B Revenue / Subscription Revenue | H17: =H9/H8 -> 0.41717122 | I17: =I9/I8 -> 0.029797944 | J17: =I17-H17 -> -0.38737328
B18: B2B-Relevant Free Users | C18: =SUM('Lightweight Freemium'!Y$8:Y$17) -> 44546.32 | D18: =SUM('Hard Paywall'!Y$8:Y$17) -> 3181.88 | E18: =D18-C18 -> -41364.44 | G18: Free Users per Subscriber | H18: =C12/C9 -> 19.3 | I18: =D12/D9 -> 1.3785714 | J18: =I18-H18 -> -17.921429
B19: Total B2B-Relevant Driver-Months | C19: =SUM('Lightweight Freemium'!Z$8:Z$17) -> 890926.41 | D19: =SUM('Hard Paywall'!Z$8:Z$17) -> 6363.7601 | E19: =D19-C19 -> -884562.65 | G19: B2B Leads per 1,000 Active Users | H19: =(C20/C8)*1000 -> 3.03975 | I19: =D20/D8 -> 0.000217125 | J19: =I19-H19 -> -3.0395329
B20: B2B Leads Generated | C20: =SUM('Lightweight Freemium'!AF$8:AF$17) -> 668.19481 | D20: =SUM('Hard Paywall'!AF$8:AF$17) -> 47.7282 | E20: =D20-C20 -> -620.4666
B21: Activated B2B Customers | C21: =SUM('Lightweight Freemium'!AH$8:AH$17) -> 267.27792 | D21: =SUM('Hard Paywall'!AH$8:AH$17) -> 19.09128 | E21: =D21-C21 -> -248.18664
